attractor/__init__.py
attractor/attractor.py
attractor/colormap.py
attractor/complex_path.py
attractor/file_writer.py
attractor/frame.py
attractor/generic.py
attractor/map_collapse.py
attractor/modMenu.py
attractor/opts.py
attractor/png.py
attractor/render_class.py
attractor/space.py
attractor/terminal.py
attractor/utils.py
attractor/view.py
attractor_tools-0.2.1.dist-info/licenses/LICENSE
attractor_tools-0.2.1.dist-info/METADATA
attractor_tools-0.2.1.dist-info/WHEEL
attractor_tools-0.2.1.dist-info/top_level.txt
attractor_tools-0.2.1.dist-info/RECORD
