Metadata-Version: 2.4
Name: attractor-tools
Version: 0.2.1
Summary: An API to animate the Simon fractal
Home-page: https://github.com/beasty79/attractor_api
Author: Silas Schimpeler
Author-email: "Silas .S" <silasfelix2005@gmail.com>
License: MIT
Keywords: video,attractor,rendering,simon,multiprocessing
Classifier: Programming Language :: Python :: 3
Classifier: License :: OSI Approved :: MIT License
Classifier: Operating System :: OS Independent
Requires-Python: >=3.9
License-File: LICENSE
Requires-Dist: matplotlib
Requires-Dist: numpy
Requires-Dist: numba
Requires-Dist: opencv-python
Requires-Dist: pyqt6
Provides-Extra: dev
Requires-Dist: pytest; extra == "dev"
Requires-Dist: black; extra == "dev"
Requires-Dist: mypy; extra == "dev"
Dynamic: author
Dynamic: home-page
Dynamic: license-file
Dynamic: requires-python
